pydateparser/__init__.py
pydateparser/_core_date_parser.py
pydateparser/_errors.py
pydateparser/_loggers.py
pydateparser/_utils.py
pydateparser/_validators.py
pydateparser/date_formats.py
pydateparser/date_parser.py
pydateparser/core/__init__.py
pydateparser/core/_core_date_matcher.py
pydateparser/core/_core_date_patterns.py
tests/__init__.py
tests/test_failures.py
tests/test_parser.py
pydateparser-0.2.6.dist-info/LICENSE-MIT
pydateparser-0.2.6.dist-info/METADATA
pydateparser-0.2.6.dist-info/WHEEL
pydateparser-0.2.6.dist-info/top_level.txt
pydateparser-0.2.6.dist-info/RECORD
