Metadata-Version: 2.1
Name: pydateparser
Version: 0.2.6
Summary: date and time parsing library.
Home-page: https://github.com/GLibAi/pydateparser
Author: glib.ai
Author-email: 
Maintainer: Samit Shah
Maintainer-email: samit@glib.ai
License: MIT
Keywords: date,time,datetime,parser
Platform: UNKNOWN
Classifier: Development Status :: 4 - Beta
Classifier: Intended Audience :: Developers
Classifier: License :: OSI Approved :: MIT License
Classifier: Natural Language :: English
Classifier: Operating System :: OS Independent
Classifier: Programming Language :: Python :: 3.6
Classifier: Programming Language :: Python :: Implementation :: CPython
